one_chat_platform/__init__.py
one_chat_platform/message_sender.py
one_chat_platform/one_chat_platform.py
one_chat_platform-0.0.5.dist-info/METADATA
one_chat_platform-0.0.5.dist-info/WHEEL
one_chat_platform-0.0.5.dist-info/top_level.txt
one_chat_platform-0.0.5.dist-info/RECORD
