Metadata-Version: 2.1
Name: one-chat-platform
Version: 0.0.5
Author: Pargorn Ruasijan (xNewz)
Author-email: pargorn.ru@gmail.com
Classifier: Programming Language :: Python :: 3
Classifier: License :: OSI Approved :: MIT License
Classifier: Operating System :: OS Independent
Requires-Python: >=3.6
Requires-Dist: requests
Requires-Dist: urllib3
